envoy/base/runner/__init__.py
envoy/base/runner/abstract.py
envoy/base/runner/decorators.py
envoy/base/runner/py.typed
envoy/base/runner/runner.py
envoy.base.runner-0.1.1.dist-info/METADATA
envoy.base.runner-0.1.1.dist-info/WHEEL
envoy.base.runner-0.1.1.dist-info/namespace_packages.txt
envoy.base.runner-0.1.1.dist-info/top_level.txt
envoy.base.runner-0.1.1.dist-info/RECORD
