Metadata-Version: 2.1
Name: envoy.base.runner
Version: 0.1.1
Summary: "Runner definitions used in Envoy proxy's CI"
Home-page: https://github.com/envoyproxy/pytooling/tree/main/envoy.base.runner
Author: Ryan Northey
Author-email: ryan@synca.io
Maintainer: Ryan Northey
Maintainer-email: ryan@synca.io
License: Apache Software License 2.0
Platform: UNKNOWN
Requires-Dist: abstracts (>=0.0.12)
Requires-Dist: coloredlogs
Requires-Dist: envoy.abstract.command (>=0.0.4)
Requires-Dist: frozendict
Requires-Dist: verboselogs
